[
    { "_id": "A101", "title": "Ball Bounce Assignment", "course": "RS101" },
    { "_id": "A102", "title": "Rotoscope Intro", "course": "RS101" },
    { "_id": "A103", "title": "Maya 3D Character", "course": "RS101" },
    { "_id": "A201", "title": "Ecology Textbook Reading", "course": "RS102" },
    { "_id": "A202", "title": "DNA Analysis", "course": "RS102" },
    { "_id": "A203", "title": "Evolution Worksheet", "course": "RS102" },
    { "_id": "A301", "title": "Periodic Table Reading", "course": "RS103" },
    { "_id": "A302", "title": "Non-Metals Worksheet", "course": "RS103" },
    { "_id": "A303", "title": "Atom Project", "course": "RS103" }
  ]